cle_utilities/__init__.py
cle_utilities/cle_log.py
cle_utilities/cledataclasses.py
cle_utilities-0.0.2.dist-info/LICENSE
cle_utilities-0.0.2.dist-info/METADATA
cle_utilities-0.0.2.dist-info/WHEEL
cle_utilities-0.0.2.dist-info/top_level.txt
cle_utilities-0.0.2.dist-info/RECORD
