Metadata-Version: 2.1
Name: cle-utilities
Version: 0.0.2
Summary: A logging package which will help to implement the cle capabilities and design the requests to be sent to cle api.
Author-email: Adeep Malmotra <Adeep.Malmotra@ibm.com>
Keywords: cle,logging,automated alert,exceptions
Classifier: Programming Language :: Python :: 3
Classifier: Development Status :: 1 - Planning
Classifier: Operating System :: OS Independent
Requires-Python: >=3.9
License-File: LICENSE
Requires-Dist: datetime
Requires-Dist: requests
Requires-Dist: requests-oauthlib
Requires-Dist: toml
